pdf_mailmerge/.DS_Store
pdf_mailmerge/.gitignore
pdf_mailmerge/__init__.py
pdf_mailmerge/config.yml
pdf_mailmerge/html/Test.html
pdf_mailmerge/pdfs/Test.pdf
pdf_mailmerge/produce_html.py
pdf_mailmerge/produce_pdfs.py
pdf_mailmerge-0.1.1.dist-info/LICENSE
pdf_mailmerge-0.1.1.dist-info/WHEEL
pdf_mailmerge-0.1.1.dist-info/METADATA
pdf_mailmerge-0.1.1.dist-info/RECORD
