Metadata-Version: 2.1
Name: pdf-mailmerge
Version: 0.1.1
Summary: easy command line mail merge to pdf
Author: Joshua
Author-email: joshua.flies.planes@gmail.org
Requires-Python: >=3.7.1,<4.0.0
Classifier: Programming Language :: Python :: 3
Classifier: Programming Language :: Python :: 3.8
Classifier: Programming Language :: Python :: 3.9
Requires-Dist: Jinja2 (>=2.11.3,<3.0.0)
Requires-Dist: PyYAML (>=5.4.1,<6.0.0)
Requires-Dist: argparse (>=1.4.0,<2.0.0)
Requires-Dist: numpy (>=1.20.1,<2.0.0)
Requires-Dist: pandas (>=1.2.3,<2.0.0)
Requires-Dist: pdfkit (>=0.6.1,<0.7.0)
Requires-Dist: tqdm (>=4.59.0,<5.0.0)
